{
    "children": [{
        "children": [
            {
                "name": "collection",
                "value": "no"
            },
            {
                "children": [{
                    "name": "mainTitle",
                    "value": "The Room"
                }],
                "name": "title"
            },
            {
                "name": "typeOfLicensing",
                "value": "typeOfLicensingInCopyright"
            },
            {
                "children": [
                    {
                        "name": "id",
                        "value": "movingImage:4933363327647860"
                    },
                    {
                        "children": [
                            {
                                "name": "linkedRecordType",
                                "value": "recordType"
                            },
                            {
                                "name": "linkedRecordId",
                                "value": "movingImage"
                            }
                        ],
                        "name": "type"
                    },
                    {
                        "children": [
                            {
                                "name": "linkedRecordType",
                                "value": "user"
                            },
                            {
                                "name": "linkedRecordId",
                                "value": "141414"
                            }
                        ],
                        "name": "createdBy"
                    },
                    {
                        "children": [
                            {
                                "name": "linkedRecordType",
                                "value": "system"
                            },
                            {
                                "name": "linkedRecordId",
                                "value": "alvin"
                            }
                        ],
                        "name": "dataDivider"
                    },
                    {
                        "name": "tsCreated",
                        "value": "2018-09-26 12:07:58.927"
                    },
                    {
                        "repeatId": "0",
                        "children": [
                            {
                                "children": [
                                    {
                                        "name": "linkedRecordType",
                                        "value": "user"
                                    },
                                    {
                                        "name": "linkedRecordId",
                                        "value": "141414"
                                    }
                                ],
                                "name": "updatedBy"
                            },
                            {
                                "name": "tsUpdated",
                                "value": "2018-09-26 12:07:58.927"
                            }
                        ],
                        "name": "updated"
                    },
                    {
                        "repeatId": "1",
                        "children": [
                            {
                                "children": [
                                    {
                                        "name": "linkedRecordType",
                                        "value": "user"
                                    },
                                    {
                                        "name": "linkedRecordId",
                                        "value": "141414"
                                    }
                                ],
                                "name": "updatedBy"
                            },
                            {
                                "name": "tsUpdated",
                                "value": "2018-09-26 12:08:08.860"
                            }
                        ],
                        "name": "updated"
                    }
                ],
                "name": "recordInfo"
            }
        ],
        "name": "movingImage"
    }],
    "name": "recordList"
}