{
    "children": [
        {
            "repeatId": "12",
            "children": [
                {
                    "name": "type",
                    "value": "metadataGroup"
                },
                {
                    "name": "key",
                    "value": "nameInData"
                },
                {
                    "name": "id",
                    "value": "recordInfoSystemOneGroup"
                },
                {
                    "name": "value",
                    "value": "recordInfo"
                },
                {
                    "name": "dataDivider",
                    "value": "systemOne"
                }
            ],
            "name": "storageTerm"
        },
        {
            "repeatId": "16",
            "children": [
                {
                    "name": "type",
                    "value": "metadataGroup"
                },
                {
                    "name": "key",
                    "value": "nameInData"
                },
                {
                    "name": "id",
                    "value": "systemOneUserRoleRelationGroup"
                },
                {
                    "name": "value",
                    "value": "userRole"
                },
                {
                    "name": "dataDivider",
                    "value": "systemOne"
                }
            ],
            "name": "storageTerm"
        },
        {
            "repeatId": "74",
            "children": [
                {
                    "name": "type",
                    "value": "metadataGroup"
                },
                {
                    "name": "key",
                    "value": "nameInData"
                },
                {
                    "name": "id",
                    "value": "systemOneUserNewGroup"
                },
                {
                    "name": "value",
                    "value": "user"
                },
                {
                    "name": "dataDivider",
                    "value": "systemOne"
                }
            ],
            "name": "storageTerm"
        },
        {
            "repeatId": "94",
            "children": [
                {
                    "name": "type",
                    "value": "systemOneUser"
                },
                {
                    "name": "key",
                    "value": "userId"
                },
                {
                    "name": "id",
                    "value": "131313"
                },
                {
                    "name": "value",
                    "value": "fitnesseAdmin@system.cora.uu.se"
                },
                {
                    "name": "dataDivider",
                    "value": "systemOne"
                }
            ],
            "name": "storageTerm"
        },
        {
            "repeatId": "95",
            "children": [
                {
                    "name": "type",
                    "value": "systemOneUser"
                },
                {
                    "name": "key",
                    "value": "userId"
                },
                {
                    "name": "id",
                    "value": "121212"
                },
                {
                    "name": "value",
                    "value": "fitnesseUser@system.cora.uu.se"
                },
                {
                    "name": "dataDivider",
                    "value": "systemOne"
                }
            ],
            "name": "storageTerm"
        },
        {
            "repeatId": "96",
            "children": [
                {
                    "name": "type",
                    "value": "systemOneUser"
                },
                {
                    "name": "key",
                    "value": "userId"
                },
                {
                    "name": "id",
                    "value": "141414"
                },
                {
                    "name": "value",
                    "value": "jsClientUser@system.cora.uu.se"
                },
                {
                    "name": "dataDivider",
                    "value": "systemOne"
                }
            ],
            "name": "storageTerm"
        }
    ],
    "name": "collectedData"
}