{
    "children": [{
        "children": [
            {
                "children": [
                    {
                        "children": [
                            {
                                "name": "linkedRecordType",
                                "value": "system"
                            },
                            {
                                "name": "linkedRecordId",
                                "value": "alvin"
                            }
                        ],
                        "name": "dataDivider"
                    },
                    {
                        "name": "id",
                        "value": "movingImage:1120208924952282"
                    },
                    {
                        "children": [
                            {
                                "name": "linkedRecordType",
                                "value": "recordType"
                            },
                            {
                                "name": "linkedRecordId",
                                "value": "movingImage"
                            }
                        ],
                        "name": "type"
                    },
                    {
                        "children": [
                            {
                                "name": "linkedRecordType",
                                "value": "user"
                            },
                            {
                                "name": "linkedRecordId",
                                "value": "141414"
                            }
                        ],
                        "name": "createdBy"
                    },
                    {
                        "name": "tsCreated",
                        "value": "2018-08-13 08:55:24.524"
                    },
                    {
                        "repeatId": "0",
                        "children": [
                            {
                                "children": [
                                    {
                                        "name": "linkedRecordType",
                                        "value": "user"
                                    },
                                    {
                                        "name": "linkedRecordId",
                                        "value": "141414"
                                    }
                                ],
                                "name": "updatedBy"
                            },
                            {
                                "name": "tsUpdated",
                                "value": "2018-08-13 08:55:24.524"
                            }
                        ],
                        "name": "updated"
                    }
                ],
                "name": "recordInfo"
            },
            {
                "name": "collection",
                "value": "yes"
            },
            {
                "name": "typeOfLicensing",
                "value": "typeOfLicensingPublicDomainMark"
            },
            {
                "children": [{
                    "children": [{
                        "repeatId": "0",
                        "children": [{
                            "name": "extentText",
                            "value": ""
                        }],
                        "name": "extent"
                    }],
                    "name": "extents"
                }],
                "name": "physicalDescription"
            },
            {
                "repeatId": "0",
                "children": [{
                    "children": [{
                        "name": "otherPhysicalDescriptionNote",
                        "value": ""
                    }],
                    "name": "otherPhysicalDescription"
                }],
                "name": "otherPhysicalDescriptions"
            },
            {
                "children": [{
                    "repeatId": "0",
                    "children": [{
                        "name": "dateNote",
                        "value": ""
                    }],
                    "name": "otherDate"
                }],
                "name": "otherDates"
            }
        ],
        "name": "movingImage"
    }],
    "name": "recordList"
}